apicurioregistryclient/__init__.py
apicurioregistryclient/api_client.py
apicurioregistryclient/configuration.py
apicurioregistryclient/exceptions.py
apicurioregistryclient/model_utils.py
apicurioregistryclient/rest.py
apicurioregistryclient/api/__init__.py
apicurioregistryclient/api/admin_api.py
apicurioregistryclient/api/artifact_rules_api.py
apicurioregistryclient/api/artifacts_api.py
apicurioregistryclient/api/global_rules_api.py
apicurioregistryclient/api/metadata_api.py
apicurioregistryclient/api/search_api.py
apicurioregistryclient/api/system_api.py
apicurioregistryclient/api/users_api.py
apicurioregistryclient/api/versions_api.py
apicurioregistryclient/apis/__init__.py
apicurioregistryclient/model/__init__.py
apicurioregistryclient/model/artifact_meta_data.py
apicurioregistryclient/model/artifact_owner.py
apicurioregistryclient/model/artifact_reference.py
apicurioregistryclient/model/artifact_search_results.py
apicurioregistryclient/model/artifact_state.py
apicurioregistryclient/model/artifact_type.py
apicurioregistryclient/model/configuration_property.py
apicurioregistryclient/model/content_create_request.py
apicurioregistryclient/model/download_ref.py
apicurioregistryclient/model/editable_meta_data.py
apicurioregistryclient/model/error.py
apicurioregistryclient/model/if_exists.py
apicurioregistryclient/model/limits.py
apicurioregistryclient/model/log_configuration.py
apicurioregistryclient/model/log_level.py
apicurioregistryclient/model/named_log_configuration.py
apicurioregistryclient/model/named_log_configuration_all_of.py
apicurioregistryclient/model/properties.py
apicurioregistryclient/model/role_mapping.py
apicurioregistryclient/model/role_type.py
apicurioregistryclient/model/rule.py
apicurioregistryclient/model/rule_type.py
apicurioregistryclient/model/rule_violation_cause.py
apicurioregistryclient/model/rule_violation_error.py
apicurioregistryclient/model/rule_violation_error_all_of.py
apicurioregistryclient/model/searched_artifact.py
apicurioregistryclient-0.6.2.dist-info/LICENSE
apicurioregistryclient-0.6.2.dist-info/METADATA
apicurioregistryclient-0.6.2.dist-info/WHEEL
apicurioregistryclient-0.6.2.dist-info/top_level.txt
apicurioregistryclient-0.6.2.dist-info/RECORD
