Metadata-Version: 2.1
Name: apicurioregistryclient
Version: 0.6.2
Summary: Apicurio Registry API [v2]
Home-page: 
Author: Apicurio
Author-email: apicurio@lists.jboss.org
License: Apache 2.0
Keywords: OpenAPI,OpenAPI-Generator,Apicurio Registry API [v2]
Requires-Python: >=3.6
License-File: LICENSE
Requires-Dist: urllib3 (>=1.25.3)
Requires-Dist: python-dateutil
